ansys/sherlock/core/__init__.py
ansys/sherlock/core/analysis.py
ansys/sherlock/core/common.py
ansys/sherlock/core/errors.py
ansys/sherlock/core/grpc_stub.py
ansys/sherlock/core/launcher.py
ansys/sherlock/core/layer.py
ansys/sherlock/core/lifecycle.py
ansys/sherlock/core/model.py
ansys/sherlock/core/parts.py
ansys/sherlock/core/project.py
ansys/sherlock/core/pysherlock_logging.py
ansys/sherlock/core/sherlock.py
ansys/sherlock/core/stackup.py
ansys/sherlock/core/types/__init__.py
ansys/sherlock/core/types/analysis_types.py
ansys/sherlock/core/types/common_types.py
ansys/sherlock/core/types/layer_types.py
ansys/sherlock/core/types/lifecycle_types.py
ansys/sherlock/core/types/parts_types.py
ansys/sherlock/core/types/project_types.py
ansys/sherlock/core/types/stackup_types.py
ansys/sherlock/core/utils/__init__.py
ansys/sherlock/core/utils/version_check.py
ansys_sherlock_core-1.0.0.dist-info/licenses/LICENSE
ansys_sherlock_core-1.0.0.dist-info/WHEEL
ansys_sherlock_core-1.0.0.dist-info/METADATA
ansys_sherlock_core-1.0.0.dist-info/RECORD
