Metadata-Version: 2.4
Name: ansys-sherlock-core
Version: 1.0.0
Summary: A python wrapper for Ansys Sherlock
Author-email: "ANSYS, Inc." <pyansys.core@ansys.com>
Maintainer-email: "ANSYS, Inc." <pyansys.core@ansys.com>
Requires-Python: >=3.10,<4
Classifier: Development Status :: 4 - Beta
Classifier: Intended Audience :: Science/Research
Classifier: Topic :: Scientific/Engineering :: Information Analysis
Classifier: License :: OSI Approved :: MIT License
Classifier: Operating System :: OS Independent
Classifier: Programming Language :: Python :: 3.10
Classifier: Programming Language :: Python :: 3.11
Classifier: Programming Language :: Python :: 3.12
Classifier: Programming Language :: Python :: 3.13
License-File: LICENSE
Requires-Dist: ansys-api-sherlock==0.1.53
Requires-Dist: grpcio>=1.17, <1.68.0
Requires-Dist: protobuf>=3.20
Requires-Dist: pydantic>=2.9.2
Requires-Dist: ansys-sphinx-theme==1.6.4 ; extra == "doc"
Requires-Dist: jupyter_sphinx==0.5.3 ; extra == "doc"
Requires-Dist: matplotlib==3.10.8 ; extra == "doc"
Requires-Dist: numpydoc==1.10.0 ; extra == "doc"
Requires-Dist: pandas==2.3.3 ; extra == "doc"
Requires-Dist: Sphinx==8.1.3 ; extra == "doc"
Requires-Dist: sphinxemoji==0.3.2 ; extra == "doc"
Requires-Dist: sphinx-autodoc-typehints==3.0.1 ; extra == "doc"
Requires-Dist: sphinx-copybutton==0.5.2 ; extra == "doc"
Requires-Dist: sphinx-design==0.6.1 ; extra == "doc"
Requires-Dist: sphinx-gallery==0.20.0 ; extra == "doc"
Requires-Dist: sphinx-notfound-page==1.1.0 ; extra == "doc"
Requires-Dist: grpcio>=1.17, <1.68.0 ; extra == "tests"
Requires-Dist: protobuf==5.28.0 ; extra == "tests"
Requires-Dist: pytest==9.0.2 ; extra == "tests"
Requires-Dist: pytest-cov==7.0.0 ; extra == "tests"
Project-URL: Documentation, https://sherlock.docs.pyansys.com
Project-URL: Homepage, https://github.com/ansys/pysherlock
Project-URL: Source, https://github.com/ansys/pysherlock
Project-URL: Tracker, https://github.com/ansys/pysherlock/issues
Provides-Extra: doc
Provides-Extra: tests
